moonbridge/__init__.py
moonbridge/py.typed
moonbridge/server.py
moonbridge/version_check.py
moonbridge/adapters/__init__.py
moonbridge/adapters/base.py
moonbridge/adapters/codex.py
moonbridge/adapters/kimi.py
moonbridge-0.5.1.dist-info/METADATA
moonbridge-0.5.1.dist-info/WHEEL
moonbridge-0.5.1.dist-info/entry_points.txt
moonbridge-0.5.1.dist-info/licenses/LICENSE
moonbridge-0.5.1.dist-info/RECORD
