Metadata-Version: 2.4
Name: moonbridge
Version: 0.5.1
Summary: MCP server for spawning Kimi K2.5 agents
Project-URL: Homepage, https://github.com/misty-step/moonbridge
Project-URL: Repository, https://github.com/misty-step/moonbridge
Project-URL: Issues, https://github.com/misty-step/moonbridge/issues
Author-email: Phaedrus <hello@mistystep.io>
License-Expression: MIT
License-File: LICENSE
Keywords: agent,ai,claude,kimi,mcp
Classifier: Development Status :: 4 - Beta
Classifier: Environment :: Console
Classifier: Intended Audience :: Developers
Classifier: License :: OSI Approved :: MIT License
Classifier: Programming Language :: Python :: 3
Classifier: Programming Language :: Python :: 3.11
Classifier: Programming Language :: Python :: 3.12
Classifier: Programming Language :: Python :: 3.13
Requires-Python: >=3.11
Requires-Dist: mcp>=1.0.0
Provides-Extra: dev
Requires-Dist: mypy>=1.8; extra == 'dev'
Requires-Dist: pytest-asyncio>=0.23; extra == 'dev'
Requires-Dist: pytest-mock>=3.12; extra == 'dev'
Requires-Dist: pytest>=8.0; extra == 'dev'
Requires-Dist: ruff>=0.2; extra == 'dev'
